{
  "$schema": "http://json-schema.org/draft-07/schema#",
  "title": "kind30403",
  "description": "Draft/Inactive Classified Listing (NIP-99). Same structure as kind 30402.",
  "allOf": [
    {
      "allOf": [
        {
          "$schema": "http://json-schema.org/draft-07/schema",
          "type": "object",
          "properties": {
            "content": {
              "type": "string",
              "errorMessage": "content must be a string",
              "description": "The content of the note"
            },
            "created_at": {
              "type": "integer",
              "errorMessage": "created_at must be a timestamp expressed in seconds (not milliseconds)",
              "description": "The timestamp of the note creation"
            },
            "id": {
              "allOf": [
                {
                  "allOf": [
                    {
                      "$schema": "http://json-schema.org/draft-07/schema#",
                      "type": "string",
                      "pattern": "^[a-f0-9]{64}$"
                    }
                  ]
                }
              ],
              "errorMessage": "id must be a valid hash",
              "description": "The id is a hash derived as specified in NIP-01"
            },
            "kind": {
              "type": "integer"
            },
            "pubkey": {
              "allOf": [
                {
                  "allOf": [
                    {
                      "$schema": "http://json-schema.org/draft-07/schema#",
                      "type": "string",
                      "pattern": "^[a-f0-9]{64}$"
                    }
                  ]
                }
              ],
              "errorMessage": "pubkey must be a secp256k1 public key",
              "description": "The public key of the note's author"
            },
            "sig": {
              "type": "string",
              "pattern": "^[a-f0-9]{128}$",
              "errorMessage": "sig must be 128 lowercase hex characters (64 bytes)",
              "description": "The cryptographic signature of the note"
            },
            "tags": {
              "type": "array",
              "errorMessage": "tags must be an array of valid tag tuples",
              "description": "The tags of the note",
              "items": {
                "allOf": [
                  {
                    "$schema": "http://json-schema.org/draft-07/schema#",
                    "type": "array",
                    "items": {
                      "type": "string"
                    },
                    "uniqueItems": false
                  }
                ]
              }
            }
          },
          "required": [
            "content",
            "created_at",
            "id",
            "kind",
            "pubkey",
            "sig",
            "tags"
          ],
          "additionalProperties": false
        }
      ]
    },
    {
      "type": "object",
      "properties": {
        "kind": {
          "const": 30403,
          "errorMessage": "kind must equal 30403"
        },
        "tags": {
          "type": "array",
          "items": {
            "allOf": [
              {
                "if": {
                  "type": "array",
                  "items": [
                    {
                      "const": "title"
                    }
                  ]
                },
                "then": {
                  "type": "array",
                  "minItems": 2,
                  "maxItems": 2,
                  "items": [
                    {
                      "const": "title"
                    },
                    {
                      "type": "string",
                      "minLength": 1
                    }
                  ]
                }
              },
              {
                "if": {
                  "type": "array",
                  "items": [
                    {
                      "const": "summary"
                    }
                  ]
                },
                "then": {
                  "type": "array",
                  "minItems": 2,
                  "maxItems": 2,
                  "items": [
                    {
                      "const": "summary"
                    },
                    {
                      "type": "string",
                      "minLength": 1
                    }
                  ]
                }
              },
              {
                "if": {
                  "type": "array",
                  "items": [
                    {
                      "const": "published_at"
                    }
                  ]
                },
                "then": {
                  "type": "array",
                  "minItems": 2,
                  "maxItems": 2,
                  "items": [
                    {
                      "const": "published_at"
                    },
                    {
                      "type": "string",
                      "pattern": "^[0-9]+$"
                    }
                  ]
                }
              },
              {
                "if": {
                  "type": "array",
                  "items": [
                    {
                      "const": "location"
                    }
                  ]
                },
                "then": {
                  "type": "array",
                  "minItems": 2,
                  "maxItems": 2,
                  "items": [
                    {
                      "const": "location"
                    },
                    {
                      "type": "string",
                      "minLength": 1
                    }
                  ]
                }
              },
              {
                "if": {
                  "type": "array",
                  "items": [
                    {
                      "const": "status"
                    }
                  ]
                },
                "then": {
                  "type": "array",
                  "minItems": 2,
                  "maxItems": 2,
                  "items": [
                    {
                      "const": "status"
                    },
                    {
                      "type": "string",
                      "enum": [
                        "active",
                        "sold"
                      ]
                    }
                  ]
                }
              },
              {
                "if": {
                  "type": "array",
                  "items": [
                    {
                      "const": "price"
                    }
                  ]
                },
                "then": {
                  "type": "array",
                  "minItems": 3,
                  "maxItems": 4,
                  "items": [
                    {
                      "const": "price"
                    },
                    {
                      "type": "string",
                      "pattern": "^\\d+(?:\\.\\d+)?$"
                    },
                    {
                      "type": "string",
                      "pattern": "^[A-Za-z]{3,6}$"
                    },
                    {
                      "type": "string",
                      "pattern": "^[A-Za-z]+$"
                    }
                  ]
                }
              },
              {
                "if": {
                  "type": "array",
                  "items": [
                    {
                      "const": "g"
                    }
                  ]
                },
                "then": {
                  "type": "array",
                  "minItems": 2,
                  "maxItems": 2,
                  "items": [
                    {
                      "const": "g"
                    },
                    {
                      "type": "string",
                      "pattern": "^[0-9bcdefghjkmnpqrstuvwxyz]+$"
                    }
                  ]
                }
              }
            ]
          }
        }
      }
    }
  ],
  "$id": "https://nostrability.github.io/schemata/note/kind/30403.json"
}